{"8__460fae87-cafc-3af5-85d9-fb6f60a7ea12": {}, "9__460fae87-cafc-3af5-85d9-fb6f60a7ea12": {"date_column_number": [0, 1, 3], "date_row_number": [[0], [3], [3]], "date_raw_text": [["Amount receivable from controlling entity (Refer Note 19)"], ["21"]], "date_extracted_year": [[2019], [2021]], "data_first_column": 2, "data_first_row": 1, "data_particular_end_col": 0, "data_particular_start_row": 1, "header_indices": [0], "row_header_indices": [], "year_column_header_name": ""}, "10__460fae87-cafc-3af5-85d9-fb6f60a7ea12": {}, "10__e99aa245-9d31-3147-91f4-8b5db0c21d19": {}, "6_(c)_46b432b5-a97d-306d-8d36-a0394079a39a": {"date_column_number": [1, 2], "date_row_number": [[0], [0]], "date_raw_text": [["2022"], ["2021"]], "date_extracted_year": [[2022], [2021]], "data_first_column": 2, "data_first_row": 2, "data_particular_end_col": 0, "data_particular_start_row": 2, "header_indices": [0, 1], "row_header_indices": [], "year_column_header_name": "header_col_1"}, "6_(c)_4a761b0d-5eec-3642-9de0-648c1c34b55a": {"date_column_number": [0, 1, 2, 3], "date_row_number": [[2, 15], [1], [1], [1]], "date_raw_text": [["31 December 2022", "31 December 2021"], ["2022"], ["2022"], ["2022"]], "date_extracted_year": [[2022, 2021], [2022], [2022], [2022]], "data_first_column": 1, "data_first_row": 3, "data_particular_end_col": 0, "data_particular_start_row": 2, "header_indices": [0, 1], "row_header_indices": [2, 15], "year_column_header_name": "header_col_0"}, "6_(c)_460fae87-cafc-3af5-85d9-fb6f60a7ea12": {}, "12__0a21830a-a4cd-32d0-a8a2-1e94fe17f24f": {}, "13__0a21830a-a4cd-32d0-a8a2-1e94fe17f24f": {}, "14__0a21830a-a4cd-32d0-a8a2-1e94fe17f24f": {}, "15__016f06ae-009b-3518-9f87-2bdf9e0280f3": {"date_column_number": [1, 2, 3, 4], "date_row_number": [[1], [1], [1], [1]], "date_raw_text": [["2022"], ["2021"], ["2022"], ["2021"]], "date_extracted_year": [[2022], [2021], [2022], [2021]], "data_first_column": 1, "data_first_row": 3, "data_particular_end_col": 0, "data_particular_start_row": 3, "header_indices": [0, 1, 2], "row_header_indices": [], "year_column_header_name": "header_col_1"}, "15__a1dc56e9-9f02-3149-a911-5b9fd5ce539e": {"date_column_number": [1, 2], "date_row_number": [[1], [1]], "date_raw_text": [["2022"], ["2021"]], "date_extracted_year": [[2022], [2021]], "data_first_column": 1, "data_first_row": 3, "data_particular_end_col": 0, "data_particular_start_row": 3, "header_indices": [0, 1, 2], "row_header_indices": [], "year_column_header_name": "header_col_1"}, "15__4d99b44b-b8b3-39a5-93c1-a2d099509b40": {"date_column_number": [2, 1, 2], "date_row_number": [[0], [0], [0]], "date_raw_text": [["2021"], [2022.0], ["2021"]], "date_extracted_year": [[2021], [2022], [2021]], "data_first_column": 1, "data_first_row": 2, "data_particular_end_col": 0, "data_particular_start_row": 2, "header_indices": [0, 1], "row_header_indices": [], "year_column_header_name": "header_col_1"}}